rov/__init__.py
rov/__main__.py
rov-0.6.0.dist-info/licenses/LICENSE
rov-0.6.0.dist-info/METADATA
rov-0.6.0.dist-info/WHEEL
rov-0.6.0.dist-info/entry_points.txt
rov-0.6.0.dist-info/top_level.txt
rov-0.6.0.dist-info/RECORD
