Metadata-Version: 2.4
Name: rov
Version: 0.6.0
Summary: Offline Internet route origin validation using RPKI, IRR, and RIRs delegated databases
Home-page: https://github.com/InternetHealthReport/route-origin-validator/
Author: Romain Fontugne
Author-email: romain.fontugne@gmail.com
Keywords: RPKI,IRR,delegated,Internet,routing,route origin validation
License-File: LICENSE
Requires-Dist: appdirs
Requires-Dist: py-radix
Requires-Dist: portion
Dynamic: author
Dynamic: author-email
Dynamic: description
Dynamic: description-content-type
Dynamic: home-page
Dynamic: keywords
Dynamic: license-file
Dynamic: requires-dist
Dynamic: summary
